{"_id":{"$oid":"58e2b3201517fe06a45e62f8"},"year":2017,"monthData":[{"salesmanCost":{"organized":0},"totalHours":{"organized":0},"shiftsCount":{"organized":0},"uniqueCount":{"organized":0},"saleBottlesCount":{"organized":0},"openedCount":{"organized":0},"saleAverage":{"organized":0},"monthlyEncoragement":[],"_id":{"$oid":"58e2b3201517fe06a45e62f9"},"month":1},{"salesmanCost":{"organized":0},"totalHours":{"organized":0},"shiftsCount":{"organized":0},"uniqueCount":{"organized":0},"saleBottlesCount":{"organized":0},"openedCount":{"organized":0},"saleAverage":{"organized":0},"monthlyEncoragement":[],"_id":{"$oid":"58e2b3201517fe06a45e62fa"},"month":2},{"salesmanCost":{"organized":4800},"totalHours":{"organized":160},"shiftsCount":{"organized":64},"uniqueCount":{"organized":0},"saleBottlesCount":{"organized":160},"openedCount":{"organized":128},"saleAverage":{"organized":1},"monthlyEncoragement":[],"_id":{"$oid":"58e2b3201517fe06a45e62fb"},"month":3},{"salesmanCost":{"organized":7890},"totalHours":{"organized":281},"shiftsCount":{"organized":123},"uniqueCount":{"organized":0},"saleBottlesCount":{"organized":236},"openedCount":{"organized":183},"saleAverage":{"organized":0.8398576512455516},"monthlyEncoragement":[],"_id":{"$oid":"58e2b3201517fe06a45e62fc"},"month":4},{"salesmanCost":{"organized":0},"totalHours":{"organized":0},"shiftsCount":{"organized":0},"uniqueCount":{"organized":0},"saleBottlesCount":{"organized":0},"openedCount":{"organized":0},"saleAverage":{"organized":0},"monthlyEncoragement":[],"_id":{"$oid":"58e2b3201517fe06a45e62fd"},"month":5},{"salesmanCost":{"organized":0},"totalHours":{"organized":0},"shiftsCount":{"organized":0},"uniqueCount":{"organized":0},"saleBottlesCount":{"organized":0},"openedCount":{"organized":0},"saleAverage":{"organized":0},"monthlyEncoragement":[],"_id":{"$oid":"58e2b3201517fe06a45e62fe"},"month":6},{"salesmanCost":{"organized":0},"totalHours":{"organized":0},"shiftsCount":{"organized":0},"uniqueCount":{"organized":0},"saleBottlesCount":{"organized":0},"openedCount":{"organized":0},"saleAverage":{"organized":0},"monthlyEncoragement":[],"_id":{"$oid":"58e2b3201517fe06a45e62ff"},"month":7},{"salesmanCost":{"organized":0},"totalHours":{"organized":0},"shiftsCount":{"organized":0},"uniqueCount":{"organized":0},"saleBottlesCount":{"organized":0},"openedCount":{"organized":0},"saleAverage":{"organized":0},"monthlyEncoragement":[],"_id":{"$oid":"58e2b3201517fe06a45e6300"},"month":8},{"salesmanCost":{"organized":0},"totalHours":{"organized":0},"shiftsCount":{"organized":0},"uniqueCount":{"organized":0},"saleBottlesCount":{"organized":0},"openedCount":{"organized":0},"saleAverage":{"organized":0},"monthlyEncoragement":[],"_id":{"$oid":"58e2b3201517fe06a45e6301"},"month":9},{"salesmanCost":{"organized":0},"totalHours":{"organized":0},"shiftsCount":{"organized":0},"uniqueCount":{"organized":0},"saleBottlesCount":{"organized":0},"openedCount":{"organized":0},"saleAverage":{"organized":0},"monthlyEncoragement":[],"_id":{"$oid":"58e2b3201517fe06a45e6302"},"month":10},{"salesmanCost":{"organized":0},"totalHours":{"organized":0},"shiftsCount":{"organized":0},"uniqueCount":{"organized":0},"saleBottlesCount":{"organized":0},"openedCount":{"organized":0},"saleAverage":{"organized":0},"monthlyEncoragement":[],"_id":{"$oid":"58e2b3201517fe06a45e6303"},"month":11},{"salesmanCost":{"organized":0},"totalHours":{"organized":0},"shiftsCount":{"organized":0},"uniqueCount":{"organized":0},"saleBottlesCount":{"organized":0},"openedCount":{"organized":0},"saleAverage":{"organized":0},"monthlyEncoragement":[],"_id":{"$oid":"58e2b3201517fe06a45e6304"},"month":12}],"__v":0}
